natural_lang/__init__.py
natural_lang/chunks.py
natural_lang-0.0.2.dist-info/METADATA
natural_lang-0.0.2.dist-info/WHEEL
natural_lang-0.0.2.dist-info/licenses/LICENSE
natural_lang-0.0.2.dist-info/RECORD
